ibm_cos_sdk_s3transfer-2.0.0.dist-info/DESCRIPTION.rst
ibm_cos_sdk_s3transfer-2.0.0.dist-info/METADATA
ibm_cos_sdk_s3transfer-2.0.0.dist-info/metadata.json
ibm_cos_sdk_s3transfer-2.0.0.dist-info/RECORD
ibm_cos_sdk_s3transfer-2.0.0.dist-info/top_level.txt
ibm_cos_sdk_s3transfer-2.0.0.dist-info/WHEEL
ibm_s3transfer/__init__.py
ibm_s3transfer/compat.py
ibm_s3transfer/copies.py
ibm_s3transfer/delete.py
ibm_s3transfer/download.py
ibm_s3transfer/exceptions.py
ibm_s3transfer/futures.py
ibm_s3transfer/manager.py
ibm_s3transfer/subscribers.py
ibm_s3transfer/tasks.py
ibm_s3transfer/upload.py
ibm_s3transfer/utils.py
s3transfer/__init__.py
s3transfer/compat.py
s3transfer/copies.py
s3transfer/delete.py
s3transfer/download.py
s3transfer/exceptions.py
s3transfer/futures.py
s3transfer/manager.py
s3transfer/subscribers.py
s3transfer/tasks.py
s3transfer/upload.py
s3transfer/utils.py
