Metadata-Version: 2.0
Name: ibm-cos-sdk-s3transfer
Version: 2.0.0
Summary: IBM S3 Transfer Manager
Home-page: https://github.com/ibm/ibm-cos-sdk-python-s3transfer
Author: IBM
Author-email: UNKNOWN
License: Apache License 2.0
Platform: UNKNOWN
Classifier: Development Status :: 3 - Alpha
Classifier: Intended Audience :: Developers
Classifier: Natural Language :: English
Classifier: License :: OSI Approved :: Apache Software License
Classifier: Programming Language :: Python
Classifier: Programming Language :: Python :: 2.6
Classifier: Programming Language :: Python :: 2.7
Classifier: Programming Language :: Python :: 3
Classifier: Programming Language :: Python :: 3.3
Classifier: Programming Language :: Python :: 3.4
Classifier: Programming Language :: Python :: 3.5
Classifier: Programming Language :: Python :: 3.6
Requires-Dist: ibm-cos-sdk-core>=2.0.0,==2.*
Requires-Dist: futures>=2.2.0,<4.0.0; python_version=="2.6" or python_version=="2.7"
